colab_dc333/README.md
colab_dc333/__init__.py
colab_dc333/fix.sh
colab_dc333/google.py
colab_dc333/nsys.sh
colab_dc333/nvidia.py
colab_dc333/run.py
colab_dc333/train.py
colab_dc333-0.0.3.dist-info/METADATA
colab_dc333-0.0.3.dist-info/WHEEL
colab_dc333-0.0.3.dist-info/licenses/LICENSE
colab_dc333-0.0.3.dist-info/RECORD
